MyBaleCloud/balecloud.py
MyBaleCloud/messager.py
MyBaleCloud-2.1.4.dist-info/LICENSE.txt
MyBaleCloud-2.1.4.dist-info/METADATA
MyBaleCloud-2.1.4.dist-info/WHEEL
MyBaleCloud-2.1.4.dist-info/top_level.txt
MyBaleCloud-2.1.4.dist-info/RECORD
